{
    "labelTextSize": "0.875rem",
    "boxShadow": "none",
    "widgetName": "enter_creds",
    "backgroundColor": "white",
    "rightColumn": 49,
    "dynamicHeight": "FIXED",
    "widgetId": "osjwvca1uy",
    "topRow": 1,
    "bottomRow": 67,
    "parentRowSpace": 10,
    "isVisible": true,
    "type": "FORM_WIDGET",
    "parentId": "0",
    "isLoading": false,
    "shouldScrollContents": false,
    "parentColumnSpace": 19.8125,
    "dynamicTriggerPathList": [],
    "leftColumn": 17,
    "dynamicBindingPathList": [],
    "borderRadius": "0px",
    "children": [{
        "labelTextSize": "0.875rem",
        "boxShadow": "none",
        "widgetName": "Canvas1",
        "rightColumn": 554.75,
        "detachFromLayout": true,
        "widgetId": "k1hymf7gq9",
        "containerStyle": "none",
        "topRow": 0,
        "bottomRow": 660,
        "parentRowSpace": 1,
        "isVisible": true,
        "canExtend": false,
        "type": "CANVAS_WIDGET",
        "version": 1,
        "parentId": "osjwvca1uy",
        "minHeight": 660,
        "isLoading": false,
        "parentColumnSpace": 1,
        "dynamicTriggerPathList": [],
        "leftColumn": 0,
        "dynamicBindingPathList": [],
        "borderRadius": "0px"
    }],
    "maxDynamicHeight": 9000,
    "minDynamicHeight": 4
}