{
    "boxShadow": "none",
    "iconSVG": "/static/media/icon.1a5defb3c19b4cac4a27829d1f979e4c.svg",
    "labelText": "Type of Industries*:",
    "topRow": 89,
    "labelWidth": 5,
    "type": "SELECT_WIDGET",
    "serverSideFiltering": false,
    "defaultOptionValue": "",
    "animateLoading": true,
    "leftColumn": 32,
    "dynamicBindingPathList": [
        {"key": "accentColor"},
        {"key": "borderRadius"}
    ],
    "labelStyle": "BOLD",
    "placeholderText": "Select option",
    "isDisabled": false,
    "isRequired": true,
    "dynamicHeight": "AUTO_HEIGHT",
    "accentColor": "{{appsmith.theme.colors.primaryColor}}",
    "isVisible": true,
    "version": 1,
    "isLoading": false,
    "borderRadius": "{{appsmith.theme.borderRadius.appBorderRadius}}",
    "originalBottomRow": 97,
    "mobileBottomRow": 55,
    "widgetName": "Select3",
    "isFilterable": false,
    "dynamicPropertyPathList": [{"key": "sourceData"}],
    "displayName": "Select",
    "searchTags": ["dropdown"],
    "bottomRow": 97,
    "parentRowSpace": 10,
    "hideCard": false,
    "mobileRightColumn": 53,
    "shouldScrollContents": true,
    "parentColumnSpace": 11.75,
    "dynamicTriggerPathList": [],
    "labelPosition": "Top",
    "sourceData": "[{\n    \"label\": \"MANUFACTURING\",\n    \"value\": \"MANUFACTURING\"\n}, {\n    \"label\": \"DISTRIBUTION\",\n    \"value\": \"DISTRIBUTION\"\n}, {\n    \"label\": \"WHOLESALE\",\n    \"value\": \"WHOLESALE\"\n}, {\n    \"label\": \"TRADING\",\n    \"value\": \"TRADING\"\n}, {\n    \"label\": \"BROKING\",\n    \"value\": \"BROKING\"\n}, {\n    \"label\": \"SERVICE PROVIDER\",\n    \"value\": \"SERVICE_PROVIDER\"\n}, {\n    \"label\": \"IMPORTING\",\n    \"value\": \"IMPORTING\"\n}, {\n    \"label\": \"EXPORTING\",\n    \"value\": \"EXPORTING\"\n}, {\n    \"label\": \"AGRICULTURE\",\n    \"value\": \"AGRICULTURE\"\n}, {\n    \"label\": \"DEALERS\",\n    \"value\": \"DEALERS\"\n}, {\n    \"label\": \"OTHERS\",\n    \"value\": \"OTHERS\"\n}]",
    "key": "5ghi2iteob",
    "labelTextSize": "1.25rem",
    "isDeprecated": false,
    "rightColumn": 63,
    "widgetId": "6oxijjcntr",
    "optionValue": "value",
    "minWidth": 450,
    "parentId": "bkscj2iujp",
    "labelAlignment": "left",
    "renderMode": "CANVAS",
    "mobileTopRow": 48,
    "optionLabel": "label",
    "responsiveBehavior": "fill",
    "originalTopRow": 89,
    "mobileLeftColumn": 33,
    "maxDynamicHeight": 9000,
    "minDynamicHeight": 4
}