{
  "gitSyncId": "63d76535285dc00849ba9c5c_640ec3dd80f7a01fe4f52bb8",
  "id": "User Details_card_type",
  "pluginId": "postgres-plugin",
  "pluginType": "DB",
  "unpublishedAction": {
    "actionConfiguration": {
      "body": "SELECT \"public\".\"cards\".\"kit_id\" AS \"kit_id\", \"public\".\"cards\".\"last4_digits\" AS \"l4d\", \"public\".\"cards\".\"status\" AS \"status\", \"Corporates\".\"corp_type\" AS \"corp_type\", \"Bins\".\"program_type\" AS \"app_type\"\nFROM \"public\".\"cards\"\nLEFT JOIN \"public\".\"corporates\" \"Corporates\" ON \"public\".\"cards\".\"corporate_id\" = \"Corporates\".\"id\" LEFT JOIN \"public\".\"card_programs\" \"Card Programs\" ON \"public\".\"cards\".\"card_program_id\" = \"Card Programs\".\"id\" LEFT JOIN \"public\".\"bins\" \"Bins\" ON \"Card Programs\".\"bin_id\" = \"Bins\".\"bin_number\"\nWHERE \"public\".\"cards\".\"kit_id\" = '{{cardlist.selectedRow.kit_id}}'",
      "encodeParamsToggle": true,
      "paginationType": "NONE",
      "pluginSpecifiedTemplates": [
        {
          "value": false
        }
      ],
      "timeoutInMillisecond": 1000000000
    },
    "confirmBeforeExecute": false,
    "datasource": {
      "id": "MatrixReadReplicauat",
      "isAutoGenerated": false,
      "name": "MatrixReadReplicaProd",
      "pluginId": "postgres-plugin"
    },
    "dynamicBindingPathList": [
      {
        "key": "body"
      }
    ],
    "executeOnLoad": true,
    "name": "card_type",
    "pageId": "User Details",
    "userSetOnLoad": false
  }
}