{
    "boxShadow": "none",
    "mobileBottomRow": 5,
    "widgetName": "IconButton1",
    "onClick": "{{closeModal('details_modal');}}",
    "buttonColor": "{{appsmith.theme.colors.primaryColor}}",
    "displayName": "Icon button",
    "iconSVG": "/static/media/icon.b08054586989b185a0801e9a34f8ad49.svg",
    "searchTags": [
        "click",
        "submit"
    ],
    "topRow": 1,
    "bottomRow": 5,
    "parentRowSpace": 10,
    "type": "ICON_BUTTON_WIDGET",
    "hideCard": false,
    "mobileRightColumn": 62,
    "animateLoading": true,
    "parentColumnSpace": 17.5,
    "dynamicTriggerPathList": [{"key": "onClick"}],
    "leftColumn": 58,
    "dynamicBindingPathList": [{"key": "buttonColor"}],
    "isDisabled": false,
    "key": "21x6t6svb7",
    "isDeprecated": false,
    "rightColumn": 62,
    "iconName": "cross",
    "widgetId": "ns9e7wgk21",
    "minWidth": 50,
    "isVisible": true,
    "version": 1,
    "parentId": "oz5hq756jz",
    "tags": ["Buttons"],
    "renderMode": "CANVAS",
    "isLoading": false,
    "mobileTopRow": 1,
    "responsiveBehavior": "hug",
    "borderRadius": "0.375rem",
    "mobileLeftColumn": 58,
    "buttonVariant": "SECONDARY"
}