{
    "boxShadow": "none",
    "widgetName": "Input1",
    "displayName": "Input",
    "iconSVG": "/static/media/icon.9f505595.svg",
    "topRow": 8,
    "bottomRow": 12,
    "parentRowSpace": 10,
    "labelWidth": 5,
    "autoFocus": false,
    "type": "INPUT_WIDGET_V2",
    "hideCard": false,
    "animateLoading": true,
    "parentColumnSpace": 6.9375,
    "dynamicTriggerPathList": [],
    "resetOnSubmit": true,
    "leftColumn": 3,
    "dynamicBindingPathList": [
        {"key": "accentColor"},
        {"key": "borderRadius"}
    ],
    "labelPosition": "Left",
    "labelStyle": "",
    "inputType": "PASSWORD",
    "placeholderText": "",
    "isDisabled": false,
    "key": "0os31l3386",
    "labelTextSize": "0.875rem",
    "isRequired": true,
    "rightColumn": 42,
    "dynamicHeight": "FIXED",
    "widgetId": "0orx7t52q6",
    "accentColor": "{{appsmith.theme.colors.primaryColor}}",
    "isVisible": true,
    "label": "",
    "version": 2,
    "parentId": "hdqq2b0twr",
    "labelAlignment": "left",
    "renderMode": "CANVAS",
    "isLoading": false,
    "borderRadius": "{{appsmith.theme.borderRadius.appBorderRadius}}",
    "maxDynamicHeight": 9000,
    "isSpellCheck": false,
    "iconAlign": "left",
    "defaultText": "",
    "minDynamicHeight": 4
}